sspilib/__init__.py
sspilib/_credential.py
sspilib/_filetime.py
sspilib/_sec_context.py
sspilib/py.typed
sspilib/raw/__init__.py
sspilib/raw/_context_attributes.cp313-win_amd64.pyd
sspilib/raw/_context_attributes.pyi
sspilib/raw/_credential.cp313-win_amd64.pyd
sspilib/raw/_credential.pyi
sspilib/raw/_credential_attributes.cp313-win_amd64.pyd
sspilib/raw/_credential_attributes.pyi
sspilib/raw/_message.cp313-win_amd64.pyd
sspilib/raw/_message.pyi
sspilib/raw/_ntstatus.cp313-win_amd64.pyd
sspilib/raw/_ntstatus.pyi
sspilib/raw/_security_buffer.cp313-win_amd64.pyd
sspilib/raw/_security_buffer.pyi
sspilib/raw/_security_context.cp313-win_amd64.pyd
sspilib/raw/_security_context.pyi
sspilib/raw/_security_package.cp313-win_amd64.pyd
sspilib/raw/_security_package.pyi
sspilib/raw/_text.cp313-win_amd64.pyd
sspilib/raw/_winerror.py
sspilib-0.4.0.dist-info/licenses/LICENSE
sspilib-0.4.0.dist-info/METADATA
sspilib-0.4.0.dist-info/WHEEL
sspilib-0.4.0.dist-info/top_level.txt
sspilib-0.4.0.dist-info/RECORD
