Metadata-Version: 2.4
Name: sspilib
Version: 0.4.0
Summary: SSPI API bindings for Python
Author-email: Jordan Borean <jborean93@gmail.com>
License-Expression: MIT
Project-URL: homepage, https://github.com/jborean93/sspilib
Keywords: sspi,kerberos,negotiate
Classifier: Development Status :: 4 - Beta
Classifier: Programming Language :: Python :: 3
Classifier: Programming Language :: Python :: 3.9
Classifier: Programming Language :: Python :: 3.10
Classifier: Programming Language :: Python :: 3.11
Classifier: Programming Language :: Python :: 3.12
Classifier: Programming Language :: Python :: 3.13
Classifier: Programming Language :: Python :: 3.14
Requires-Python: >=3.9
License-File: LICENSE
Dynamic: license-file
